music21py/__init__.py
music21py-0.0.2.dist-info/LICENSE
music21py-0.0.2.dist-info/METADATA
music21py-0.0.2.dist-info/WHEEL
music21py-0.0.2.dist-info/entry_points.txt
music21py-0.0.2.dist-info/top_level.txt
music21py-0.0.2.dist-info/RECORD
