Metadata-Version: 2.1
Name: music21py
Version: 0.0.2
Summary: Convert between music21 and musicpy objects
Home-page: https://github.com/oxygen-dioxide/music21py
Author: oxygen dioxide
Author-email: 1463567152@qq.com
License: MIT License
Platform: UNKNOWN
Classifier: License :: OSI Approved :: MIT License
Classifier: Programming Language :: Python
Classifier: Programming Language :: Python :: 3
Classifier: Programming Language :: Python :: 3.9
Classifier: Programming Language :: Python :: 3.8
Classifier: Programming Language :: Python :: 3.7
Classifier: Programming Language :: Python :: 3.6
Classifier: Programming Language :: Python :: 3.5
Classifier: Topic :: Multimedia :: Sound/Audio :: MIDI
Classifier: Topic :: Multimedia :: Sound/Audio :: Sound Synthesis
Classifier: Programming Language :: Python :: Implementation :: CPython
Requires-Python: >=3.5.0
License-File: LICENSE
Requires-Dist: music21
Requires-Dist: musicpy
